ml_eval_pro/__init__.py
ml_eval_pro/adverserial_test_cases/__init__.py
ml_eval_pro/adverserial_test_cases/adversarial_attack.py
ml_eval_pro/adverserial_test_cases/adversarial_attack_factory.py
ml_eval_pro/adverserial_test_cases/adversarial_attack_substitute/__init__.py
ml_eval_pro/adverserial_test_cases/adversarial_attack_substitute/adversarial_attack_substitute.py
ml_eval_pro/adverserial_test_cases/adversarial_attack_substitute/adversarial_attack_zoo.py
ml_eval_pro/adverserial_test_cases/adversarial_attack_substitute/adversrial_attack_hopskipjump.py
ml_eval_pro/adverserial_test_cases/adversarial_attack_substitute/model/__init__.py
ml_eval_pro/adverserial_test_cases/adversarial_attack_substitute/model/adversarial_attack_substitute_classification.py
ml_eval_pro/adverserial_test_cases/adversarial_attack_substitute/model/adversarial_attack_substitute_model.py
ml_eval_pro/adverserial_test_cases/adversarial_attack_substitute/model/adversarial_attack_substitute_model_factory.py
ml_eval_pro/adverserial_test_cases/adversarial_attack_substitute/model/adversarial_attack_substitute_regression.py
ml_eval_pro/carbon/__init__.py
ml_eval_pro/carbon/carbon_emission/__init__.py
ml_eval_pro/carbon/carbon_emission/carbon.py
ml_eval_pro/carbon/carbon_emission/carbon_calculator.py
ml_eval_pro/carbon/inference_time/__init__.py
ml_eval_pro/carbon/inference_time/inference_time.py
ml_eval_pro/configuration_manager/__init__.py
ml_eval_pro/configuration_manager/configuration_reader/__init__.py
ml_eval_pro/configuration_manager/configuration_reader/configuration_reader_interface.py
ml_eval_pro/configuration_manager/configuration_reader/yaml_reader.py
ml_eval_pro/configuration_manager/readers_serializers/__init__.py
ml_eval_pro/configuration_manager/readers_serializers/yaml_serializer.py
ml_eval_pro/ethical_analysis/__init__.py
ml_eval_pro/ethical_analysis/ethical_analysis.py
ml_eval_pro/ethical_analysis/feature_importance/__init__.py
ml_eval_pro-0.1.2.dist-info/LICENSE.txt
ml_eval_pro-0.1.2.dist-info/METADATA
ml_eval_pro-0.1.2.dist-info/WHEEL
ml_eval_pro-0.1.2.dist-info/top_level.txt
ml_eval_pro-0.1.2.dist-info/RECORD
